aaaaa_sanskrit.pth
sanskrit/__init__.py
sanskrit/__main__.py
sanskrit-0.2.0.dist-info/LICENSE
sanskrit-0.2.0.dist-info/METADATA
sanskrit-0.2.0.dist-info/WHEEL
sanskrit-0.2.0.dist-info/entry_points.txt
sanskrit-0.2.0.dist-info/top_level.txt
sanskrit-0.2.0.dist-info/RECORD
