Metadata-Version: 2.1
Name: sanskrit
Version: 0.2.0
Summary: Write programs in the fastest language, as confirmed by NASA.
Home-page: https://github.com/tusharsadhwani/sanskrit
Author: Tushar Sadhwani
Author-email: tushar.sadhwani000@gmail.com
License: MIT
Classifier: License :: OSI Approved :: MIT License
Classifier: Operating System :: OS Independent
Classifier: Programming Language :: Python :: 3
Classifier: Programming Language :: Python :: 3 :: Only
Classifier: Programming Language :: Python :: 3.8
Classifier: Programming Language :: Python :: 3.9
Classifier: Programming Language :: Python :: 3.10
Classifier: Programming Language :: Python :: 3.11
Classifier: Programming Language :: Python :: 3.12
Classifier: Programming Language :: Python :: Implementation :: CPython
Classifier: Typing :: Typed
Requires-Python: >=3.8
License-File: LICENSE
